postmanlite/__init__.py
postmanlite/cli.py
postmanlite/config.py
postmanlite/core.py
postmanlite/formatter.py
postmanlite/history.py
postmanlite/welcome.py
postmanlite-1.0.0.dist-info/licenses/LICENSE
postmanlite-1.0.0.dist-info/METADATA
postmanlite-1.0.0.dist-info/WHEEL
postmanlite-1.0.0.dist-info/entry_points.txt
postmanlite-1.0.0.dist-info/top_level.txt
postmanlite-1.0.0.dist-info/RECORD
