Metadata-Version: 2.4
Name: postmanlite
Version: 1.0.0
Summary: A lightweight CLI HTTP client with rich formatting
Home-page: https://github.com/postmanlite/postmanlite
Author: BenTex2006
Author-email: BenTex2006 <hello.b3xtopia@gmail.com>
License: MIT License
Project-URL: Homepage, https://github.com/postmanlite/postmanlite
Project-URL: Bug Tracker, https://github.com/postmanlite/postmanlite/issues
Project-URL: Documentation, https://github.com/postmanlite/postmanlite#readme
Project-URL: Source Code, https://github.com/postmanlite/postmanlite
Project-URL: Funding, https://ko-fi.com/postmanlite
Keywords: http,cli,api,testing,requests,postman,curl,rest,api-client,http-client,command-line,terminal
Classifier: Development Status :: 5 - Production/Stable
Classifier: Intended Audience :: Developers
Classifier: Topic :: Internet :: WWW/HTTP
Classifier: Topic :: Software Development :: Testing
Classifier: Topic :: System :: Networking
Classifier: Topic :: Utilities
Classifier: License :: OSI Approved :: MIT License
Classifier: Programming Language :: Python :: 3
Classifier: Programming Language :: Python :: 3.7
Classifier: Programming Language :: Python :: 3.8
Classifier: Programming Language :: Python :: 3.9
Classifier: Programming Language :: Python :: 3.10
Classifier: Programming Language :: Python :: 3.11
Classifier: Programming Language :: Python :: 3.12
Classifier: Operating System :: OS Independent
Classifier: Environment :: Console
Requires-Python: >=3.7
License-File: LICENSE
Requires-Dist: requests>=2.28.0
Requires-Dist: click>=8.0.0
Requires-Dist: rich>=12.0.0
Requires-Dist: setuptools>=68.0.0
Requires-Dist: build>=0.10.0
Requires-Dist: twine>=4.0.2
Provides-Extra: dev
Requires-Dist: pytest>=6.0; extra == "dev"
Requires-Dist: pytest-cov; extra == "dev"
Requires-Dist: black; extra == "dev"
Requires-Dist: flake8; extra == "dev"
Requires-Dist: mypy; extra == "dev"
Requires-Dist: twine; extra == "dev"
Requires-Dist: build; extra == "dev"
Dynamic: author
Dynamic: home-page
Dynamic: license-file
Dynamic: requires-python
